{
  "name": "estabelecimento",
  "base": "PersistedModel",
  "idInjection": false,
  "options": {
    "validateUpsert": true
  },
  "mysql": {
    "schema": "shareprice",
    "table": "esprEstabelecimento"
  },
  "properties": {
    "cdestabelecimento": {
      "type": "number",
      "id": true,
      "required": true,
      "length": null,
      "precision": 10,
      "scale": 0,
      "mysql": {
        "columnName": "cdEstabelecimento",
        "dataType": "int",
        "dataLength": null,
        "dataPrecision": 10,
        "dataScale": 0,
        "nullable": "N"
      },
      "_selectable": false
    },
    "delogo": {
      "type": "string",
      "required": false,
      "length": 65535,
      "precision": null,
      "scale": null,
      "mysql": {
        "columnName": "deLogo",
        "dataType": "text",
        "dataLength": 65535,
        "dataPrecision": null,
        "dataScale": null,
        "nullable": "Y"
      },
      "_selectable": true
    },
    "devicinity": {
      "type": "string",
      "required": false,
      "length": 65535,
      "precision": null,
      "scale": null,
      "mysql": {
        "columnName": "deVicinity",
        "dataType": "text",
        "dataLength": 65535,
        "dataPrecision": null,
        "dataScale": null,
        "nullable": "Y"
      },
      "_selectable": true
    },
    "dtcadastro": {
      "type": "date",
      "required": false,
      "length": null,
      "precision": null,
      "scale": null,
      "mysql": {
        "columnName": "dtCadastro",
        "dataType": "datetime",
        "dataLength": null,
        "dataPrecision": null,
        "dataScale": null,
        "nullable": "Y"
      },
      "_selectable": true
    },
    "nmestabelecimento": {
      "type": "string",
      "required": false,
      "length": 100,
      "precision": null,
      "scale": null,
      "mysql": {
        "columnName": "nmEstabelecimento",
        "dataType": "varchar",
        "dataLength": 100,
        "dataPrecision": null,
        "dataScale": null,
        "nullable": "Y"
      },
      "_selectable": true
    },
    "nulatitude": {
      "type": "number",
      "required": false,
      "length": null,
      "precision": 10,
      "scale": 8,
      "mysql": {
        "columnName": "nuLatitude",
        "dataType": "decimal",
        "dataLength": null,
        "dataPrecision": 10,
        "dataScale": 8,
        "nullable": "Y"
      },
      "_selectable": true
    },
    "nulongitude": {
      "type": "number",
      "required": false,
      "length": null,
      "precision": 10,
      "scale": 8,
      "mysql": {
        "columnName": "nuLongitude",
        "dataType": "decimal",
        "dataLength": null,
        "dataPrecision": 10,
        "dataScale": 8,
        "nullable": "Y"
      },
      "_selectable": true
    }
  },
  "validations": [],
  "relations": {},
  "acls": [],
  "methods": {}
}
